[
  {
    "Layout": [
      "####",
      "#  #",
      "#  #",
      "#  #####",
      "#.$$ $@#",
      "#  . . #",
      "#  #####",
      "####"
    ]
  },
  {
    "Layout": [
      "  ####",
      "###  #",
      "# $.@##",
      "#  *  #",
      "#  *  #",
      "#######"
    ]
  },
  {
    "Layout": [
      "#######",
      "#     #",
      "# .$  #",
      "##.$###",
      "#  @  #",
      "# .$# #",
      "#     #",
      "#######"
    ]
  },
  {
    "Layout": [
      "######",
      "#  @ #",
      "# #$ #",
      "# .*.#",
      "###$ #",
      "#  * #",
      "#    #",
      "###  #",
      "  ####"
    ]
  },
  {
    "Layout": [
      "######",
      "#    #####",
      "#   $ $  #",
      "###$...@ #",
      "  #  #####",
      "  ####"
    ]
  },
  {
    "Layout": [
      "########",
      "#  #  ##",
      "# *#$.##",
      "# * $. #",
      "# @    #",
      "#   ####",
      "########"
    ]
  },
  {
    "Layout": [
      " ####",
      " #  #####",
      " #$   $ #",
      " # .#.  #",
      "## ### ##",
      "# $.#. #",
      "# @   $#",
      "#####  #",
      "    ####"
    ]
  },
  {
    "Layout": [
      "################",
      "#  #  #  #  #  #",
      "#  .  #  #  #  #",
      "# $#  *  #  #  #",
      "#  #  # @*  #$ #",
      "#  #  #  #  .  #",
      "#  #  #  #  #  #",
      "################"
    ]
  },
  {
    "Layout": [
      "  ####",
      " ##  #########",
      " #           #",
      " #  ##### ## ##",
      "### ## # .$.$ #",
      "# $@$  #      #",
      "# . .  ########",
      "########"
    ]
  },
  {
    "Layout": [
      "########",
      "#      #",
      "# $.#..##",
      "##$.$$@ #",
      "# $.#   #",
      "#   #####",
      "#####"
    ]
  },
  {
    "Layout": [
      "####### #####",
      "#   ..###   #",
      "#  ##.#     #",
      "# @##$# $  ##",
      "#      $ ###",
      "#  #  #  #",
      "#######  #",
      "      ####"
    ]
  },
  {
    "Layout": [
      "####",
      "#  ####",
      "#...  #",
      "#.##  ##",
      "#  $ $ #",
      "###$ $ #",
      "  #@   #",
      "  ######"
    ]
  },
  {
    "Layout": [
      " ####",
      " #  ###",
      " # *  #",
      " # *#@#",
      "## *  #",
      "#  .$##",
      "#    #",
      "######"
    ]
  },
  {
    "Layout": [
      "########",
      "#    @ #",
      "# $  $ #",
      "## ## ##",
      "# $# $#",
      "#  .. #",
      "## .. #",
      " ######"
    ]
  },
  {
    "Layout": [
      "####",
      "# @####",
      "#     ##",
      "# .#.  #",
      "##$$$$ #",
      "# . .###",
      "#    #",
      "######"
    ]
  },
  {
    "Layout": [
      "   ####",
      " ###@ #",
      " #    ##",
      "##$#.. #",
      "#  $ # #",
      "# # $  #",
      "# ..#$##",
      "##    #",
      " #  ###",
      " ####"
    ]
  },
  {
    "Layout": [
      "######",
      "#   ###",
      "#   ####",
      "## $ * ##",
      "##$#... #",
      "# $   @ #",
      "#   ##  #",
      "#########"
    ]
  },
  {
    "Layout": [
      "########",
      "#   .  #",
      "# $ #  ##",
      "# ** ** #",
      "##  # $ #",
      " #  . @ #",
      " ########"
    ]
  },
  {
    "Layout": [
      "######",
      "#    ##",
      "#.$$. ##",
      "# .$$. ##",
      "## .$$. #",
      " ## .$$.#",
      "  ## @  #",
      "   ######"
    ]
  },
  {
    "Layout": [
      "    ####",
      " ####  ##",
      " #  # * ##",
      "##.$#  * ##",
      "#   @ * * #",
      "#   #  *  #",
      "######    #",
      "    ###  ##",
      "      ####"
    ]
  },
  {
    "Layout": [
      "    #####",
      "   ##   #",
      "   #  @ #",
      "#### # ##",
      "#. .  . #",
      "#  ###  #",
      "## $ $ ##",
      " #  $ ##",
      " ###  #",
      "   ####"
    ]
  },
  {
    "Layout": [
      "##### #####",
      "#   ###   #",
      "#    ##   #",
      "##    $$ ##",
      " #  #  $ #",
      " ###  #  #",
      "   # @####",
      "   #    #",
      " ### ## #",
      " #    # #",
      " #.. .# #",
      " ## ### #",
      "  #     #",
      "  #######"
    ]
  },
  {
    "Layout": [
      "    ####",
      "    #  ###",
      "    #  . #",
      "    #  $ #",
      "    ## ########",
      " #####   ##   #",
      " #  #  *      #",
      "##.$# *@* #$.##",
      "#      *  #  #",
      "#   ##   #####",
      "######## ##",
      "     # $  #",
      "     # .  #",
      "     ###  #",
      "       ####"
    ]
  },
  {
    "Layout": [
      "    ####",
      "    #  ###",
      "    #  . #",
      "    #  $ #",
      "    ## ########",
      " #####  ###   #",
      " #  ## *      #",
      "##.$# * * #$.##",
      "#      * ##  #",
      "#   ###  #####",
      "######## ##",
      "     # $  #",
      "     # .@ #",
      "     ###  #",
      "       ####"
    ]
  },
  {
    "Layout": [
      "#####",
      "#   ##",
      "# #  #",
      "# #$.###",
      "#  .$  #",
      "# #$.# #",
      "# #.$# #",
      "#  $. @#",
      "###.$# #",
      "  #  # #",
      "  ##   #",
      "   #####"
    ]
  },
  {
    "Layout": [
      "  #####",
      "  #   #",
      "  #.# #######",
      "  # $       #",
      "  #.# ### # #",
      " ##  #   $$ #",
      " ##.# #   ###",
      "##      ###",
      "#  @ ####",
      "#   ##",
      "#####"
    ]
  },
  {
    "Layout": [
      "     ####",
      "###### .#",
      "#      .#",
      "#  #$#@.#####",
      "## #   . #  #",
      " #  ###  $$ #",
      " # #   ##$  #",
      " #         ##",
      " #  ########",
      " ####"
    ]
  },
  {
    "Layout": [
      "####  ####",
      "#  ####  #",
      "# $$  $$ #",
      "# .$..$. #",
      "## .  . ##",
      " ## @  ##",
      "  ######"
    ]
  },
  {
    "Layout": [
      "       #####",
      " #######   #",
      "##   ..# $ #",
      "# $ $..# $ #",
      "# $ #..$ $ #",
      "# $ #..   ##",
      "# @ #######",
      "#####"
    ]
  },
  {
    "Layout": [
      "###########",
      "#  *.*.*  #",
      "#   $+$   #",
      "### ### ###",
      "  #  $   #",
      "  #  #   #",
      "  #  #####",
      "  ####"
    ]
  },
  {
    "Layout": [
      "       ####",
      "  ###### .#",
      "###       #",
      "#  $$ # ..#",
      "# $  #  .##",
      "#  $$# #.###",
      "###  #     #",
      "  #    # # #",
      "  ##### @  #",
      "      #   ##",
      "      #####"
    ]
  },
  {
    "Layout": [
      "############",
      "#   .#  #  #",
      "#   .#    $###",
      "# @#.# $#  $ ##",
      "#   .   # $   ##",
      "#  ##### ##    #",
      "####   ##    # #",
      "        # #  # #",
      "        #  ##  #",
      "        ##    ##",
      "         ######"
    ]
  },
  {
    "Layout": [
      "           #######",
      "          ##     #",
      "         ##  ### #",
      "         #  $ $  ##",
      "         # $ $ $  #",
      " #########  ###   #",
      " # . . . # ## #####",
      "##        @  $ #",
      "#  . . . # #   #",
      "# ######## #####",
      "#          #",
      "############"
    ]
  },
  {
    "Layout": [
      "  #####",
      "### @ ###",
      "# $$$$$ #",
      "# ..... #",
      "#   #   #",
      "#########",
      "    #"
    ]
  },
  {
    "Layout": [
      "####",
      "#   ###",
      "# .$. #",
      "# $*  #",
      " #  *$ #",
      " # .$. #",
      " ###  @#",
      "    ####"
    ]
  },
  {
    "Layout": [
      "###########",
      "#   #     #",
      "#  .$ ##  #",
      "# #.$##.. #",
      "# ##   $$##",
      "#  #   #  #",
      "##$$   ## #",
      "# ..##$.# #",
      "#  ## $.  #",
      "#   @ #   #",
      "###########"
    ]
  },
  {
    "Layout": [
      "####",
      "#  #",
      "#  #",
      "#  #######",
      "#.$$ $ $@#",
      "#  . . . #",
      "#  #######",
      "####"
    ]
  },
  {
    "Layout": [
      "####",
      "# @#",
      "#  ###",
      "#.$$ #",
      "#  . #",
      "#  #####",
      "#.$$ $ #",
      "#  . . #",
      "#  #####",
      "####"
    ]
  },
  {
    "Layout": [
      "      ####",
      "     ##  #",
      "   ### @ #",
      "   #  $  #",
      "   #    ##",
      "  ### ###",
      "### $$ #",
      "# .....#",
      "#   $$ #",
      "# # #  #",
      "#   ####",
      "#####"
    ]
  },
  {
    "Layout": [
      "   ########",
      "   #   #  #",
      "   #      #",
      " #####$## #",
      " #   # ## #",
      " #   #  #.#",
      " ##  $  #.#",
      "  #  #  #.#",
      "  #$#####.#",
      "### #  ## #",
      "#        @#",
      "# $##  #  #",
      "#      ####",
      "########"
    ]
  },
  {
    "Layout": [
      "#########",
      "#   ##  #",
      "#@#$    #",
      "#  $$## ##",
      "##    # ##",
      "###$##.  #",
      "  #  #. .#",
      "  ##  .###",
      "   #    #",
      "   ##   #",
      "   ######"
    ]
  },
  {
    "Layout": [
      "#####",
      "#   #######",
      "#   ...   #",
      "## $ $ $  #",
      "######@####",
      "#  $ $ $ ##",
      "#   ...  #",
      "#######  #",
      "      #  #",
      "      ####"
    ]
  },
  {
    "Layout": [
      "   ####",
      "   #  #",
      "   #  ##",
      "  ##$. ####",
      "### $.$$  #",
      "#  ..@..  #",
      "#  $$.$ ###",
      "#### .$##",
      "   ##  #",
      "    #  #",
      "    ####"
    ]
  },
  {
    "Layout": [
      "  ####",
      "###  ###",
      "#      #",
      "# $ $ $#",
      "#*.*.*.#",
      "# $ $ $#",
      "#*.*.*.#",
      "# @    #",
      "########"
    ]
  },
  {
    "Layout": [
      "  ######",
      "  #  ####",
      "  # $ $ ##",
      "### #.#.###",
      "#     #   #",
      "# # #.#.# #",
      "# # $ $ # #",
      "#  #  # # #",
      "##  #   # #",
      " ##  ###  #",
      "  ##  @  ##",
      "   #######"
    ]
  },
  {
    "Layout": [
      "#####    #####",
      "#  #######   #",
      "# $ #####  $ #",
      "#  $ ###  $ ##",
      "##  $ #  $ ###",
      " ##  .... ###",
      " ### .##.####",
      " ####.##. ###",
      " ### ....  ##",
      "### $  # $  ##",
      "## $  ### $  #",
      "# $  ##### $ #",
      "#@  #######  #",
      "#####    #####"
    ]
  },
  {
    "Layout": [
      "    #######",
      "  ####   ####",
      "#### $ # $ ####",
      "#  #  $ $  #  #",
      "#      #      #",
      "#* ######### *#",
      "#  ....@....  #",
      "#* ######### *#",
      "#      #      #",
      "#  #  $ $  #  #",
      "#### $ # $ ####",
      "  ####   ####",
      "    #######"
    ]
  },
  {
    "Layout": [
      "########",
      "# @ #  ##",
      "#  *#$.##",
      "## * $. #",
      "##      #",
      " ###   ##",
      "  #######"
    ]
  },
  {
    "Layout": [
      "  ######",
      "  ##  ##",
      "###   ##",
      "#  .*$ #",
      "#  *.$@#",
      "##   ###",
      "##  ##",
      "######"
    ]
  },
  {
    "Layout": [
      "  ######",
      " ###  ##",
      "###   ##",
      "#  .*$ #",
      "#  *.$@#",
      "##   ###",
      " ##  # #",
      "  ######"
    ]
  },
  {
    "Layout": [
      "    #####",
      " ####   #",
      " #   $  #",
      "##  #$###",
      "# * .  #",
      "#  * #@#",
      "### .  #",
      "  #  ###",
      "  ####"
    ]
  },
  {
    "Layout": [
      "    #####",
      " ####   #",
      " #   $  #",
      "##  #$###",
      "# * .  #",
      "#  * #@#",
      "##  *  #",
      " # . ###",
      " ##  #",
      "  ####"
    ]
  },
  {
    "Layout": [
      "    #####",
      " ####   #",
      " #   $  #",
      "##  #$###",
      "# * .  #",
      "#  * #@#",
      "##  *  #",
      " # * .##",
      " ##   #",
      "  #####"
    ]
  },
  {
    "Layout": [
      "####",
      "#  ######",
      "#       ####",
      "# $ $   #  #####",
      "##### ###    $ #",
      "   #     $ #   #",
      "   #  @  #$#####",
      "   ##### #  .#",
      "      #  ###.#",
      "      #   ...#",
      "      #####  #",
      "          ####"
    ]
  },
  {
    "Layout": [
      "##### #####",
      "#   ###   #",
      "# #. #  # #",
      "#  $.$ $. #",
      "##  $.$. ##",
      " ##$.@.$##",
      "## .$.$  ##",
      "# .$ $.$  #",
      "# #  # .# #",
      "#   ###   #",
      "##### #####"
    ]
  },
  {
    "Layout": [
      "   #####",
      "   #   #",
      "  ## .$##",
      "####$. ####",
      "# $ $.$$  #",
      "# ...@... #",
      "#  $$.$ $ #",
      "#### .$####",
      "  ##$. ##",
      "   #   #",
      "   #####"
    ]
  },
  {
    "Layout": [
      "  #########",
      "  #       #",
      "### # # # ###",
      "#  $.$.$.$  #",
      "# #.$.$.$.# #",
      "#  $.# #.$  #",
      "# #.$ @ $.# #",
      "#  $.# #.$  #",
      "# #.$.$.$.# #",
      "#  $.$.$.$  #",
      "### # # # ###",
      "  #       #",
      "  #########"
    ]
  },
  {
    "Layout": [
      "###############",
      "#             #",
      "# # # # # # # #",
      "#  $.$.$.$.$  #",
      "# #.$.$.$.$.# #",
      "#  $.$.$.$.$  #",
      "# #.$.$.$.$.# #",
      "#  $.$.@.$.$  #",
      "# #.$.$.$.$.# #",
      "#  $.$.$.$.$  #",
      "# #.$.$.$.$.# #",
      "#  $.$.$.$.$  #",
      "# # # # # # # #",
      "#             #",
      "###############"
    ]
  },
  {
    "Layout": [
      "#################",
      "#               #",
      "#.$.$.######### #",
      "#$.$.$          #",
      "#.$.$.######### #",
      "#$.$.$          #",
      "#.$.$.######### #",
      "#       $       #",
      "# ############# #",
      "#       @       #",
      "#################"
    ]
  },
  {
    "Layout": [
      "  #####",
      " ##   ##",
      "### #  #",
      "###$.# #",
      "#  $.#@#",
      "# #$.# #",
      "# #    #",
      "#  # ###",
      "##   ##",
      " #####"
    ]
  },
  {
    "Layout": [
      "'LOMA 1a'"
    ]
  },
  {
    "Layout": [
      "########",
      "#      #",
      "# #$.@ #",
      "#  $.###",
      "# #$.#",
      "#   ##",
      "#####"
    ]
  },
  {
    "Layout": [
      "'LOMA 1b'"
    ]
  },
  {
    "Layout": [
      "#####",
      "#   ####",
      "#  $.  #",
      "## $.  #",
      " ##$.###",
      "  #@ #",
      "  ####"
    ]
  },
  {
    "Layout": [
      "'LOMA 1c'"
    ]
  },
  {
    "Layout": [
      "  ####",
      "  #  #",
      "  #  #",
      "###$.#",
      "#  $.##",
      "# #$. #",
      "#   @ #",
      "#######"
    ]
  },
  {
    "Layout": [
      "'LOMA 1d'"
    ]
  },
  {
    "Layout": [
      "##### ####",
      "#   ###  #",
      "#    ##@ #",
      "##    #$.#",
      " ##    $.#",
      "# ##  #$.#",
      "## ## #  #",
      "### ######"
    ]
  },
  {
    "Layout": [
      "'LOMA 1e'"
    ]
  },
  {
    "Layout": [
      "#####",
      "#   ####",
      "# #$.  #",
      "#  .$#@#",
      "###$.  #",
      "  #  ###",
      "  #  #",
      "  ####"
    ]
  },
  {
    "Layout": [
      "'LOMA 2a'"
    ]
  },
  {
    "Layout": [
      "  ######",
      "###    #",
      "#   ## #",
      "# #$.  #",
      "#@#.$###",
      "# #$.##",
      "#     #",
      "###   #",
      "  #####"
    ]
  },
  {
    "Layout": [
      "'LOMA 2b'"
    ]
  },
  {
    "Layout": [
      "  ######",
      "###    #",
      "#  $.# #",
      "#@#.$  #",
      "# #$.###",
      "#    #",
      "######"
    ]
  },
  {
    "Layout": [
      "'LOMA 2c'"
    ]
  },
  {
    "Layout": [
      "   #####",
      "####   #",
      "#  $.# #",
      "#@#.$  #",
      "# #$.###",
      "# #  #",
      "#    #",
      "######"
    ]
  },
  {
    "Layout": [
      "'LOMA 2d'"
    ]
  },
  {
    "Layout": [
      "  ####",
      " ##  #",
      " # . #",
      " # * #",
      "## *###",
      "#  $ #",
      "#  @ #",
      "#  ###",
      "####"
    ]
  },
  {
    "Layout": [
      "'LOMA 3a'"
    ]
  },
  {
    "Layout": [
      "####",
      "#  ####",
      "#     #",
      "#  .# #",
      "###*# ##",
      " #@*   #",
      " # $   #",
      " ###  ##",
      "   ####"
    ]
  },
  {
    "Layout": [
      "'LOMA 3b'"
    ]
  },
  {
    "Layout": [
      " #####",
      " # . #",
      " # * #",
      "## * #",
      "#  * #",
      "# @$ #",
      "#  ###",
      "####"
    ]
  },
  {
    "Layout": [
      "'LOMA 3c'"
    ]
  },
  {
    "Layout": [
      "######",
      "# .  #",
      "# *# #",
      "#@*  #",
      "# * ##",
      "##$  #",
      "#    #",
      "# # ##",
      "#   #",
      "#####"
    ]
  },
  {
    "Layout": [
      "'LOMA 3d'"
    ]
  },
  {
    "Layout": [
      "###### #",
      "#   ## #",
      "#  . #",
      "#  $ ###",
      "## * @ #",
      "###$ # #",
      "  #.#  #",
      "# #   ##",
      "# ######"
    ]
  },
  {
    "Layout": [
      "'LOMA 4a'"
    ]
  },
  {
    "Layout": [
      "#####",
      "#   ##",
      "# #. ###",
      "#  $ @ #",
      "###*   #",
      "#  $ ###",
      "# #.##",
      "#   #",
      "#####"
    ]
  },
  {
    "Layout": [
      "'LOMA 4b'"
    ]
  },
  {
    "Layout": [
      "#####",
      "#   #",
      "# . #",
      "# $ #",
      "##* ##",
      "# $  #",
      "# . @#",
      "###  #",
      "  ####"
    ]
  },
  {
    "Layout": [
      "'LOMA 4c'"
    ]
  },
  {
    "Layout": [
      " ######",
      " ###  #",
      " # . @#",
      " # $  #",
      "###* ##",
      "#  $ ##",
      "# #. #",
      "#   ##",
      "##  ##",
      "######"
    ]
  },
  {
    "Layout": [
      "'LOMA 4d'"
    ]
  },
  {
    "Layout": [
      " ####",
      " #  #",
      " #  #",
      " #  ####",
      "###$$  #",
      "#  $.  #",
      "# #..###",
      "# @# #",
      "##   #",
      "######"
    ]
  },
  {
    "Layout": [
      "'LOMA 5a'"
    ]
  },
  {
    "Layout": [
      "#####",
      "#  @####",
      "# #$$  #",
      "#  $.# #",
      "###..  #",
      "  ##   #",
      "   #####"
    ]
  },
  {
    "Layout": [
      "'LOMA 5b'"
    ]
  },
  {
    "Layout": [
      "   ####",
      "#### @#",
      "#  $$ ##",
      "# #$.  #",
      "#  ..# #",
      "####   #",
      "   #####"
    ]
  },
  {
    "Layout": [
      "'LOMA 5c'"
    ]
  },
  {
    "Layout": [
      " #####",
      " #   #",
      " # # #",
      " # @ #",
      "##$$###",
      "# $.  #",
      "# ..# #",
      "###   #",
      "  #####"
    ]
  },
  {
    "Layout": [
      "'LOMA 5d'"
    ]
  },
  {
    "Layout": [
      "  #####",
      "  ##  #",
      "###   #",
      "#  $  #",
      "# .*.##",
      "## $ #",
      "###@ #",
      "  ####"
    ]
  },
  {
    "Layout": [
      "'LOMA 6a'"
    ]
  },
  {
    "Layout": [
      "  ####",
      " ##  #",
      "###$ #",
      "# .*.#",
      "# #$ #",
      "#  @ #",
      "#   ##",
      "#####"
    ]
  },
  {
    "Layout": [
      "'LOMA 6b'"
    ]
  },
  {
    "Layout": [
      "   #####",
      "   #   ##",
      " ### #  #",
      "##  $ # #",
      "#  .*.  #",
      "# # $  ##",
      "#  #@###",
      "##   #",
      " #####"
    ]
  },
  {
    "Layout": [
      "'LOMA 6c'"
    ]
  },
  {
    "Layout": [
      "### #####",
      "#####   #",
      "### $ # #",
      "# @.*.  #",
      "# # $ ###",
      "#   #####",
      "##### ###"
    ]
  },
  {
    "Layout": [
      "'LOMA 6d'"
    ]
  },
  {
    "Layout": [
      "#####",
      "#   ##",
      "#  $ ##",
      "##$*. ##",
      " # .@  #",
      " #  #  #",
      "#####  #",
      "##  ####"
    ]
  },
  {
    "Layout": [
      "'LOMA 7a'"
    ]
  },
  {
    "Layout": [
      "#####",
      "#   ####",
      "# #@$  #",
      "#  $*. #",
      "####. ##",
      " #    #",
      " #   ##",
      " #####"
    ]
  },
  {
    "Layout": [
      "'LOMA 7b'"
    ]
  },
  {
    "Layout": [
      "  ########",
      "  #      #",
      "### #### #",
      "#  @$  # #",
      "#  $*. # #",
      "#  #.### #",
      "#  #     #",
      "##########"
    ]
  },
  {
    "Layout": [
      "'LOMA 7c'"
    ]
  },
  {
    "Layout": [
      "  ####",
      "  #  #####",
      "  #      #",
      "### ###  #",
      "# @$  #  #",
      "# $*. # ##",
      "###.### #",
      " #      #",
      " #   #  #",
      " ########"
    ]
  },
  {
    "Layout": [
      "'LOMA 7d'"
    ]
  },
  {
    "Layout": [
      "  #####",
      " ##   #",
      "###   #",
      "#  * ##",
      "# .@$##",
      "#  * ##",
      "##  ##",
      "#####"
    ]
  },
  {
    "Layout": [
      "'LOMA 8a'"
    ]
  },
  {
    "Layout": [
      " ####",
      " #  ##",
      "## * ##",
      "# .@$ #",
      "#  *  #",
      "#  #  #",
      "#######"
    ]
  },
  {
    "Layout": [
      "'LOMA 8b'"
    ]
  },
  {
    "Layout": [
      "  #####",
      " ##   #",
      "## *  #",
      "# .@$##",
      "#  *  #",
      "###   #",
      "#######"
    ]
  },
  {
    "Layout": [
      "'LOMA 8c'"
    ]
  },
  {
    "Layout": [
      " #####",
      " #   ##",
      "## #  ##",
      "# * #  #",
      "#.@$ # #",
      "# *  # #",
      "###    #",
      "  #  ###",
      "  ####"
    ]
  },
  {
    "Layout": [
      "'LOMA 8d'"
    ]
  },
  {
    "Layout": [
      "  ####",
      "  #  #",
      "###  ###",
      "## $*  #",
      "#  *. @#",
      "#   ####",
      "#  ##",
      "#####"
    ]
  },
  {
    "Layout": [
      "'LOMA 9a'"
    ]
  },
  {
    "Layout": [
      "#####",
      "#   #####",
      "#   #   #",
      "## $*@  #",
      " # *.  ##",
      " #  ####",
      " ####"
    ]
  },
  {
    "Layout": [
      "'LOMA 9b'"
    ]
  },
  {
    "Layout": [
      "  ####",
      "  #@ #",
      "  #  ##",
      "###$* ##",
      "#  *.  #",
      "#      #",
      "#####  #",
      "    ####"
    ]
  },
  {
    "Layout": [
      "'LOMA 9c'"
    ]
  },
  {
    "Layout": [
      "     ####",
      "######  #",
      "#  ##   #",
      "#   $*  #",
      "#  #*. ##",
      "##  @ ##",
      " #  ###",
      " ####"
    ]
  },
  {
    "Layout": [
      "'LOMA 9d'"
    ]
  },
  {
    "Layout": [
      "#### ###",
      "#@ ### #",
      "# $$ ###",
      "# $ .  #",
      "## ..  #",
      " #######"
    ]
  },
  {
    "Layout": [
      "'LOMA 10a'"
    ]
  },
  {
    "Layout": [
      "####",
      "#  #",
      "#@ ###",
      "# $$ ##",
      "# $ . #",
      "###.. #",
      " #   ##",
      " #   #",
      " #####"
    ]
  },
  {
    "Layout": [
      "'LOMA 10b'"
    ]
  },
  {
    "Layout": [
      "######",
      "#    #",
      "#    #",
      "## $$##",
      " # $@.#",
      " ## ..#",
      "  #####"
    ]
  },
  {
    "Layout": [
      "'LOMA 10c'"
    ]
  },
  {
    "Layout": [
      "  #####",
      "###   #",
      "# $$# #",
      "# $@. #",
      "#  .. #",
      "#######"
    ]
  },
  {
    "Layout": [
      "'LOMA 10d'"
    ]
  },
  {
    "Layout": [
      "     #####     #####     #####     #####",
      "     #   #######   #######   #######   ####",
      "     # # #  #### # #  #### # #  #### # #  ##",
      "     #       ###       ###       ###       ##",
      "    #### #    #### #    #### #    #### #    ##",
      "#######   #    ##   #    ##   #    ##   #    #",
      "#   ###    #    #    #    #    #    #    # $ #",
      "# # #  #    #    #    #    #    #    #    #  #",
      "#       #    #    #    #    #    #    #    ###",
      "### #    #    #    #    #    #    #    #    ##",
      " #   #    #    #    #    #    #    #    #    #",
      " #    #    #    #    #    #    #    #    #   #",
      " ##    #    #    #    #    #    #    #    # ###",
      " ###    #    #    #    #    #    #    #       #",
      " ####    #    #    #    #    #    #    #  # # #",
      "######    #    #    #    #    #    #    ###   #",
      "#   ###    #    #    #    #    #    #    ######",
      "# # #  #    #    #    #    #    #    #    ####",
      "#       #    #    #    #    #    #    #    ###",
      "### #    #    #    #    #    #    #    #    ##",
      " #   #    #    #    #    #    #    #    #    #",
      " #    #    #    #    #    #    #    #    #   #",
      " ##    #    #    #    #    #    #    #    # ###",
      " ###    #    #    #    #    #    #    #       #",
      " ####    #    #    #    #    #    #    #  # # #",
      "######    #    #    #    #    #    #    ###   #",
      "#   ###    #    #    #    #    #    #    ######",
      "# # #  #    #    #    #    #    #    #    ####",
      "#       #    #    #    #    #    #    #    ###",
      "### #    #    #    #    #    #    #    #    ##",
      " #   #    #    #    #    #    #    #    #    #",
      " #    #    #    #    #    #    #    #    #   #",
      " ##    #    #    #    #    #    #    #    # ###",
      " ###    #    #    #    #    #    #    #       #",
      " #  #    #    #    #    #    #    #    #  # # #",
      " # . #    #    #    #    #    #    #    ###   #",
      " #  @ #   ##    #   ##    #   ##    #   #######",
      " ##    # ####    # ####    # ####    # ####",
      "  ##       ###       ###       ###       #",
      "   ##  # # ####  # # ####  # # ####  # # #",
      "    ####   #######   #######   #######   #",
      "       #####     #####     #####     #####"
    ]
  },
  {
    "Layout": [
      "Author: David W. Skinner"
    ]
  }
]