[
  {
    "Layout": [
      " #####",
      " #   ##",
      "## * .##",
      "# $$*  #",
      "#  * . #",
      "## @ ###",
      " #####"
    ]
  },
  {
    "Layout": [
      "  ####",
      "###  ###",
      "#   *$ #",
      "# #  # #",
      "#   ** #",
      "###  #@#",
      "  # ** #",
      "  #  # #",
      "  # *. #",
      "  #  ###",
      "  ####"
    ]
  },
  {
    "Layout": [
      "######",
      "#    #",
      "# ##$###",
      "# . *  #",
      "##  * +#",
      " #  $  #",
      " # #*###",
      " #   #",
      " #####"
    ]
  },
  {
    "Layout": [
      "    ####",
      "#####  ##",
      "# .@.$. #",
      "# # $   #",
      "# ##$####",
      "#   $  ##",
      "### .   ##",
      "  ###    #",
      "    ##   #",
      "     #####"
    ]
  },
  {
    "Layout": [
      "    ####",
      "  ###  #",
      "  #    #",
      "###  # #",
      "# *$ **##",
      "# # +#  #",
      "#  #    #",
      "##    ###",
      " ######"
    ]
  },
  {
    "Layout": [
      "  ######",
      "###    #",
      "#  *##.#",
      "# #.  .#",
      "# $ $  #",
      "##$#$#@#",
      " #    .#",
      " #######"
    ]
  },
  {
    "Layout": [
      " ####",
      " #  ###",
      " # *$ #",
      " #  # #",
      "## ** #",
      "#   #@#",
      "#  ** #",
      "#   # #",
      "## *. #",
      " #  ###",
      " ####"
    ]
  },
  {
    "Layout": [
      "  ####",
      "###  #",
      "# .* ##",
      "# #   #",
      "#@**  #",
      "# #   #",
      "# $* ##",
      "###  #",
      "  ####"
    ]
  },
  {
    "Layout": [
      "  ####",
      "###  ####",
      "# $     #",
      "# . *#  #",
      "###.@#$##",
      "# . *#  #",
      "# $     #",
      "######  #",
      "     ####"
    ]
  },
  {
    "Layout": [
      " ####",
      " #  ######",
      " #       #",
      "## # #.$ #",
      "#  * ## ##",
      "# ** # @#",
      "###   * #",
      "  ####  #",
      "     ####"
    ]
  },
  {
    "Layout": [
      "   #####",
      "####   #",
      "#      #",
      "#  ##.##",
      "## #@  #",
      " #..$  #",
      "## #$###",
      "#   $ #",
      "# #   #",
      "#   ###",
      "#####"
    ]
  },
  {
    "Layout": [
      "  #####",
      "###   #",
      "#   # ##",
      "#  **+ #",
      "## * $*##",
      " # # #  #",
      " #      #",
      " ###  ###",
      "   ####"
    ]
  },
  {
    "Layout": [
      "####  ####",
      "#  ####  #",
      "#        #",
      "#  ####  #",
      "##@##. $##",
      "#  #.$* #",
      "#      ##",
      "#  #  ##",
      "#######"
    ]
  },
  {
    "Layout": [
      " #######",
      "##  #  ##",
      "# .$*$. #",
      "#   #   #",
      "##  *  ##",
      " #@ *  #",
      " #######"
    ]
  },
  {
    "Layout": [
      " #######",
      "##  #  ##",
      "#  **$. #",
      "#   #   #",
      "##  *  ##",
      " #  * @#",
      " #######"
    ]
  },
  {
    "Layout": [
      " ####",
      " #  #",
      " #. ##",
      " #$@ #",
      "## * #",
      "#  * #",
      "#  * #",
      "## * #",
      " #  ##",
      " ####"
    ]
  },
  {
    "Layout": [
      " ######",
      " #  @ ##",
      "## #   #",
      "# .*.*.#",
      "#  $ $ #",
      "#####$ #",
      "    #  #",
      "    ####"
    ]
  },
  {
    "Layout": [
      " #######",
      "##  @  ##",
      "#  ###  #",
      "# # . # #",
      "# #$. $ #",
      "# $   ###",
      "###$. #",
      "  # . #",
      "  #####"
    ]
  },
  {
    "Layout": [
      "  #####",
      "  #+ .###",
      "  #     #",
      "  ## $  #",
      " ###$####",
      "## $   #",
      "#  . * #",
      "#   #  #",
      "########"
    ]
  },
  {
    "Layout": [
      " #####",
      " #   #",
      "##*# #####",
      "# * $ *  #",
      "#   . @  #",
      "###  #*###",
      "  ##   #",
      "   #####"
    ]
  },
  {
    "Layout": [
      "  #####",
      " ##   #",
      "##  #.##",
      "# @ $  #",
      "# * *  ###",
      "##*#*#   #",
      " #       #",
      " ##  #####",
      "  ####"
    ]
  },
  {
    "Layout": [
      "#####",
      "#   #####",
      "# #   $ ##",
      "#.$.$..@ #",
      "#### #$  #",
      "   #   ###",
      "   #####"
    ]
  },
  {
    "Layout": [
      "   ####",
      " ### @##",
      "##   * ##",
      "#  ##*  #",
      "#    *  #",
      "##  #$# #",
      " #   .  #",
      " #  #####",
      " ####"
    ]
  },
  {
    "Layout": [
      "#####",
      "#   ####",
      "#    $ #",
      "## ##* ##",
      "#  #..  #",
      "#    $$ #",
      "#  #@.###",
      "#######"
    ]
  },
  {
    "Layout": [
      "##### ####",
      "#   # #  #",
      "#  $###@ #",
      "## $  $  #",
      " # ....$ #",
      " ##  #  ##",
      "  #######"
    ]
  },
  {
    "Layout": [
      "& Fran\u00e7ois Marques"
    ]
  },
  {
    "Layout": [
      "    #####",
      "#####   #",
      "#       #",
      "#  ..# ##",
      "##$# *  #",
      " # +#*  #",
      " #$ $  ##",
      " #  ####",
      " ####"
    ]
  },
  {
    "Layout": [
      " #######",
      " #  #  ###",
      " #$   $  #",
      " # .#**  #",
      "## #@ # ##",
      "#  ..#. #",
      "# $   $ #",
      "######  #",
      "     ####"
    ]
  },
  {
    "Layout": [
      " ####",
      " #  #####",
      " #      #",
      " # * *  #",
      "##$# # ##",
      "# . *#* #",
      "#       #",
      "####@ ###",
      "   ####"
    ]
  },
  {
    "Layout": [
      " ####",
      " # @##",
      "## . ###",
      "# $$$. #",
      "#..$.# #",
      "# $ $  #",
      "## .  ##",
      " ######"
    ]
  },
  {
    "Layout": [
      " #######",
      " #     #",
      " # .$. #",
      "##$. $##",
      "#  *  #",
      "# $.$##",
      "##@. #",
      " #####"
    ]
  },
  {
    "Layout": [
      " #####",
      " #   ##",
      "##* ..##",
      "#   #  #",
      "# *    #",
      "# * # ##",
      "##  $$#",
      " ### @#",
      "   ####"
    ]
  },
  {
    "Layout": [
      "  #######",
      " ##  #  #",
      "##   $$ #",
      "#  #.#  #",
      "#  .+. ##",
      "#  #.#$##",
      "## $  $ #",
      " ####   #",
      "    #####"
    ]
  },
  {
    "Layout": [
      "#####",
      "#   ###",
      "#     #",
      "## #. ###",
      "#@***$* #",
      "#       #",
      "#  #  ###",
      "#######"
    ]
  },
  {
    "Layout": [
      "  ####",
      " ##  ###",
      "## ..  #",
      "#  *   #",
      "# $$ ###",
      "## *.#",
      " # $ #",
      " # * #",
      " # @##",
      " ####"
    ]
  },
  {
    "Layout": [
      "   #####",
      " ###   #",
      "##   #@##",
      "# . *$. #",
      "# # $   #",
      "# #$#$###",
      "#  .. #",
      "#######"
    ]
  },
  {
    "Layout": [
      "   ####",
      "####  #",
      "# . * #",
      "#@# * #",
      "#   * ##",
      "##$**  #",
      " #     #",
      " ###  ##",
      "   ####"
    ]
  },
  {
    "Layout": [
      " ####",
      " #  ####",
      " #   * ##",
      "## #  $.##",
      "#  #$.#  #",
      "#  $  $@ #",
      "#  #..#  #",
      "##########"
    ]
  },
  {
    "Layout": [
      "  #####",
      "  #   #",
      "### . ##",
      "#  *$* ##",
      "# # * * #",
      "#    * @#",
      "###  ####",
      "  ####"
    ]
  },
  {
    "Layout": [
      "  ####",
      "  #  #",
      "  #* #",
      "###  ###",
      "# .*   #",
      "# #$ # #",
      "#  @** #",
      "##   ###",
      " #  ##",
      " ####"
    ]
  },
  {
    "Layout": [
      "   #####",
      " ###   #",
      "##     #",
      "# *** ##",
      "#  *@ #",
      "# .*$##",
      "##   #",
      " ##  #",
      "  ####"
    ]
  },
  {
    "Layout": [
      ":"
    ]
  }
]